feature_fabrica/__init__.py
feature_fabrica/core.py
feature_fabrica/exceptions.py
feature_fabrica/models.py
feature_fabrica/promise_manager.py
feature_fabrica/transform/__init__.py
feature_fabrica/transform/aggregate.py
feature_fabrica/transform/base.py
feature_fabrica/transform/datetime.py
feature_fabrica/transform/generic.py
feature_fabrica/transform/importer.py
feature_fabrica/transform/math.py
feature_fabrica/transform/string.py
feature_fabrica/transform/utils.py
feature_fabrica/utils.py
feature_fabrica/yaml_parser.py
feature_fabrica-1.3.1.dist-info/LICENSE.txt
feature_fabrica-1.3.1.dist-info/METADATA
feature_fabrica-1.3.1.dist-info/WHEEL
feature_fabrica-1.3.1.dist-info/RECORD
