Metadata-Version: 2.1
Name: feature-fabrica
Version: 1.3.1
Summary: Open-source Python library designed to improve engineering practices and transparency in feature engineering.
Author: Chingis Oinar
Author-email: chingisoinar@gmail.com
Requires-Python: >=3.10,<4.0
Classifier: Programming Language :: Python :: 3
Classifier: Programming Language :: Python :: 3.10
Classifier: Programming Language :: Python :: 3.11
Classifier: Programming Language :: Python :: 3.12
Requires-Dist: beartype (>=0.18.5,<0.19.0)
Requires-Dist: easydict (>=1.13,<2.0)
Requires-Dist: graphviz (>=0.20.3,<0.21.0)
Requires-Dist: hydra-core (>=1.3.2,<2.0.0)
Requires-Dist: jaxtyping (>=0.2.34,<0.3.0)
Requires-Dist: loguru (>=0.7.2,<0.8.0)
Requires-Dist: numpy (>=1.26.2,<2.0.0)
Requires-Dist: pydantic (>=2.8.2,<3.0.0)
Requires-Dist: scikit-learn (>=1.5.1,<2.0.0)
